HISTORY.rst
LICENSE
MANIFEST.in
README.rst
setup.py
heroku/__init__.py
heroku/api.py
heroku/compat.py
heroku/core.py
heroku/helpers.py
heroku/models.py
heroku/structures.py
heroku.egg-info/PKG-INFO
heroku.egg-info/SOURCES.txt
heroku.egg-info/dependency_links.txt
heroku.egg-info/requires.txt
heroku.egg-info/top_level.txt