Metadata-Version: 1.1
Name: heroku
Version: 0.1.3
Summary: Heroku API Wrapper.
Home-page: https://github.com/heroku/heroku.py
Author: Kenneth Reitz
Author-email: kenneth@heroku.com
License: MIT
Platform: UNKNOWN
Classifier: Development Status :: 5 - Production/Stable
Classifier: Intended Audience :: Developers
Classifier: Natural Language :: English
Classifier: License :: OSI Approved :: MIT License
Classifier: Programming Language :: Python
Classifier: Programming Language :: Python :: 2.6
Classifier: Programming Language :: Python :: 2.7
